ubirch/__init__.py
ubirch/ubirch_api.py
ubirch/ubirch_ks.py
ubirch/ubirch_protocol.py
ubirch_protocol-3.1.0.dist-info/LICENSE
ubirch_protocol-3.1.0.dist-info/METADATA
ubirch_protocol-3.1.0.dist-info/WHEEL
ubirch_protocol-3.1.0.dist-info/top_level.txt
ubirch_protocol-3.1.0.dist-info/RECORD
