Metadata-Version: 2.1
Name: ubirch-protocol
Version: 3.1.0
Summary: A ubirch-protocol implementation for python.
Home-page: https://github.com/ubirch/ubirch-protocol-python
Author: Matthias L. Jugel
Author-email: matthias.jugel@ubirch.com
Classifier: Programming Language :: Python :: 3
Classifier: License :: OSI Approved :: Apache Software License
Classifier: Operating System :: OS Independent
License-File: LICENSE
Requires-Dist: msgpack (>=0.6.0)
Requires-Dist: ed25519 (>=1.4)
Requires-Dist: pyjks (>=17.1.1)
Requires-Dist: requests (>=2.19.1)
